MLProvCodeGen/__init__.py
MLProvCodeGen/_version.py
MLProvCodeGen/app.py
MLProvCodeGen/handlers.py
MLProvCodeGen/labextension/package.json
MLProvCodeGen/labextension/static/747.d0e592ad0a89d94053a4.js
MLProvCodeGen/labextension/static/763.8ec200c4789c1f5c239e.js
MLProvCodeGen/labextension/static/remoteEntry.a55b4268a8ac7473a2aa.js
MLProvCodeGen/labextension/static/style.js
MLProvCodeGen/labextension/static/third-party-licenses.json
MLProvCodeGen-0.1.0.data/data/etc/jupyter/jupyter_notebook_config.d/MLProvCodeGen.json
MLProvCodeGen-0.1.0.data/data/etc/jupyter/jupyter_server_config.d/MLProvCodeGen.json
MLProvCodeGen-0.1.0.data/data/share/jupyter/labextensions/MLProvCodeGen/install.json
MLProvCodeGen-0.1.0.data/data/share/jupyter/labextensions/MLProvCodeGen/package.json
MLProvCodeGen-0.1.0.data/data/share/jupyter/labextensions/MLProvCodeGen/static/747.d0e592ad0a89d94053a4.js
MLProvCodeGen-0.1.0.data/data/share/jupyter/labextensions/MLProvCodeGen/static/763.8ec200c4789c1f5c239e.js
MLProvCodeGen-0.1.0.data/data/share/jupyter/labextensions/MLProvCodeGen/static/remoteEntry.a55b4268a8ac7473a2aa.js
MLProvCodeGen-0.1.0.data/data/share/jupyter/labextensions/MLProvCodeGen/static/style.js
MLProvCodeGen-0.1.0.data/data/share/jupyter/labextensions/MLProvCodeGen/static/third-party-licenses.json
MLProvCodeGen-0.1.0.dist-info/LICENSE
MLProvCodeGen-0.1.0.dist-info/METADATA
MLProvCodeGen-0.1.0.dist-info/WHEEL
MLProvCodeGen-0.1.0.dist-info/top_level.txt
MLProvCodeGen-0.1.0.dist-info/RECORD
